rtlpy/__init__.py
rtlpy/_info.py
rtlpy/py.typed
rtlpy/utils.py
rtlpy/uvm.py
rtlpy/_uvm_templates/uvm_reg.jinja
rtlpy/_uvm_templates/uvm_reg_block.jinja
rtlpy/_uvm_templates/uvm_reg_block_paged.jinja
rtlpy/design/__init__.py
rtlpy/design/memory.py
rtlpy/design/types.py
rtlpy-1.1.0.dist-info/LICENSE
rtlpy-1.1.0.dist-info/METADATA
rtlpy-1.1.0.dist-info/WHEEL
rtlpy-1.1.0.dist-info/top_level.txt
rtlpy-1.1.0.dist-info/RECORD
